LICENSE
MANIFEST.in
README
runtests
setup.py
contrib/replaceNodeType.py
contrib/xpycscope/pycscope-indexer
contrib/xpycscope/xpycscope.el
doc/dwh-cscopeFormat.txt
pycscope/__init__.py
pycscope/__main__.py
pycscope.egg-info/PKG-INFO
pycscope.egg-info/SOURCES.txt
pycscope.egg-info/dependency_links.txt
pycscope.egg-info/entry_points.txt
pycscope.egg-info/top_level.txt
test/__init__.py
test/badsyntax.py
test/imports.py
test/issue0018.py
test/testgenfiles.py
test/testimports.py
test/testissues.py
test/testparsefile.py
test/testparsesource.py
test/testwork.py
test/testwriteindex.py