Metadata-Version: 1.1
Name: pycscope
Version: 1.2
Summary: Generates a cscope index of Python source trees
Home-page: http://github.com/portante/pycscope
Author: Peter Portante
Author-email: peter.a.portante@gmail.com
License: GPLv2
Keywords: pycscope cscope indexing
Platform: UNKNOWN
Classifier: Development Status :: 5 - Production/Stable
Classifier: Environment :: Console
Classifier: Intended Audience :: Developers
Classifier: License :: OSI Approved :: GNU General Public License v2 (GPLv2)
Classifier: Programming Language :: Python :: 2.7
Classifier: Programming Language :: Python :: 3
Classifier: Topic :: Software Development
Classifier: Topic :: Text Editors
Classifier: Topic :: Text Editors :: Integrated Development Environments (IDE)
Classifier: Topic :: Text Editors :: Text Processing
Classifier: Topic :: Text Processing :: Indexing
Classifier: Topic :: Utilities
